zen_generator/__init__.py
zen_generator/cli.py
zen_generator/core/__init__.py
zen_generator/core/ast_utils.py
zen_generator/core/exception.py
zen_generator/core/formatting.py
zen_generator/core/io.py
zen_generator/core/parsing.py
zen_generator/core/type_system.py
zen_generator/generators/__init__.py
zen_generator/generators/asyncapi.py
zen_generator/generators/common_python.py
zen_generator/generators/python.py
zen_generator-0.1.8.dist-info/licenses/LICENSE
zen_generator-0.1.8.dist-info/METADATA
zen_generator-0.1.8.dist-info/WHEEL
zen_generator-0.1.8.dist-info/entry_points.txt
zen_generator-0.1.8.dist-info/top_level.txt
zen_generator-0.1.8.dist-info/RECORD
