Metadata-Version: 2.4
Name: zen-generator
Version: 0.1.8
Summary: A bidirectional Python code generator that converts between AsyncAPI 3.0 specifications and Python code (pure Python or FastAPI implementations).
Author-email: "Carlo Bertini [WaYdotNET]" <waydotnet@gmail.com>
License: MIT
Project-URL: Home Page, https://pypi.org/project/zen-generator/
Project-URL: Documentation, https://github.com/WaYdotNET/zen-generator/blob/main/README.md
Project-URL: GitHub, https://github.com/WaYdotNET/zen-generator
Project-URL: Changelog, https://github.com/WaYdotNET/zen-generator/blob/main/CHANGELOG.md
Project-URL: Bug Reports, https://github.com/WaYdotNET/zen-generator/discussions
Keywords: asyncapi,code generator,python,fastapi
Classifier: Development Status :: 5 - Production/Stable
Classifier: Operating System :: OS Independent
Classifier: Environment :: Web Environment
Classifier: Programming Language :: Python
Classifier: Topic :: Software Development :: Libraries :: Python Modules
Classifier: License :: OSI Approved :: MIT License
Classifier: Programming Language :: Python :: 3
Classifier: Programming Language :: Python :: 3.8
Classifier: Programming Language :: Python :: 3.9
Classifier: Programming Language :: Python :: 3.10
Classifier: Programming Language :: Python :: 3.11
Requires-Python: >=3.10
License-File: LICENSE
Requires-Dist: pyyaml>=6.0.2
Requires-Dist: ruff>=0.9.9
Requires-Dist: typer>=0.15.2
Requires-Dist: yamllint>=1.35.1
Dynamic: license-file
